garf/io/__init__.py
garf/io/exceptions.py
garf/io/formatter.py
garf/io/reader.py
garf/io/telemetry.py
garf/io/writer.py
garf/io/writers/__init__.py
garf/io/writers/abs_writer.py
garf/io/writers/bigquery_writer.py
garf/io/writers/console_writer.py
garf/io/writers/csv_writer.py
garf/io/writers/file_writer.py
garf/io/writers/json_writer.py
garf/io/writers/null_writer.py
garf/io/writers/sheets_writer.py
garf/io/writers/sqldb_writer.py
garf_io/__init__.py
garf_io/exceptions.py
garf_io/formatter.py
garf_io/reader.py
garf_io/telemetry.py
garf_io/writer.py
garf_io/writers/__init__.py
garf_io/writers/abs_writer.py
garf_io/writers/bigquery_writer.py
garf_io/writers/console_writer.py
garf_io/writers/csv_writer.py
garf_io/writers/file_writer.py
garf_io/writers/json_writer.py
garf_io/writers/null_writer.py
garf_io/writers/sheets_writer.py
garf_io/writers/sqldb_writer.py
garf_io-1.1.0.dist-info/METADATA
garf_io-1.1.0.dist-info/WHEEL
garf_io-1.1.0.dist-info/entry_points.txt
garf_io-1.1.0.dist-info/top_level.txt
garf_io-1.1.0.dist-info/RECORD
