Metadata-Version: 2.4
Name: garf-io
Version: 1.1.0
Summary: Handles reading queries and writing GarfReport from garf-core package
Author-email: Andrei Markin <andrey.markin.ppc@gmail.com>, "Google Inc. (gTech gPS CSE team)" <no-reply@google.com>
License: Apache 2.0
Classifier: Programming Language :: Python :: 3 :: Only
Classifier: Programming Language :: Python :: 3.8
Classifier: Programming Language :: Python :: 3.9
Classifier: Programming Language :: Python :: 3.10
Classifier: Programming Language :: Python :: 3.11
Classifier: Programming Language :: Python :: 3.12
Classifier: Programming Language :: Python :: 3.13
Classifier: Programming Language :: Python :: 3.14
Classifier: Intended Audience :: Developers
Classifier: Topic :: Software Development :: Libraries :: Python Modules
Classifier: Operating System :: OS Independent
Classifier: License :: OSI Approved :: Apache Software License
Requires-Python: >=3.8
Requires-Dist: garf-core>=1.0.0
Requires-Dist: smart_open
Requires-Dist: rich
Requires-Dist: opentelemetry-api
Provides-Extra: test
Requires-Dist: pytest; extra == "test"
Requires-Dist: pytest-cov; extra == "test"
Requires-Dist: pytest-asyncio; extra == "test"
Requires-Dist: pandas; extra == "test"
Provides-Extra: bq
Requires-Dist: google-cloud-bigquery; extra == "bq"
Requires-Dist: google-cloud-bigquery-storage; extra == "bq"
Requires-Dist: pandas; extra == "bq"
Requires-Dist: smart_open[gcs]; extra == "bq"
Requires-Dist: pandas-gbq; extra == "bq"
Provides-Extra: sqlalchemy
Requires-Dist: sqlalchemy; extra == "sqlalchemy"
Requires-Dist: pandas; extra == "sqlalchemy"
Provides-Extra: sheets
Requires-Dist: gspread; extra == "sheets"
Provides-Extra: all
Requires-Dist: garf-io[bq,sheets,sqlalchemy]; extra == "all"
